tabulize/__init__.py
tabulize/records.py
tabulize/sqltable.py
tabulize/to_sql.py
tabulize-0.1.2.dist-info/LICENSE
tabulize-0.1.2.dist-info/METADATA
tabulize-0.1.2.dist-info/WHEEL
tabulize-0.1.2.dist-info/top_level.txt
tabulize-0.1.2.dist-info/RECORD
